odoo/addons/shopinvader_product_brand_image/README.rst
odoo/addons/shopinvader_product_brand_image/__init__.py
odoo/addons/shopinvader_product_brand_image/__manifest__.py
odoo/addons/shopinvader_product_brand_image/data/ir_export_brand.xml
odoo/addons/shopinvader_product_brand_image/demo/backend_demo.xml
odoo/addons/shopinvader_product_brand_image/i18n/shopinvader_product_brand.pot
odoo/addons/shopinvader_product_brand_image/i18n/shopinvader_product_brand_image.pot
odoo/addons/shopinvader_product_brand_image/models/__init__.py
odoo/addons/shopinvader_product_brand_image/models/shopinvader_backend.py
odoo/addons/shopinvader_product_brand_image/models/shopinvader_brand.py
odoo/addons/shopinvader_product_brand_image/readme/CONTRIBUTORS.rst
odoo/addons/shopinvader_product_brand_image/readme/DESCRIPTION.rst
odoo/addons/shopinvader_product_brand_image/static/description/index.html
odoo/addons/shopinvader_product_brand_image/tests/__init__.py
odoo/addons/shopinvader_product_brand_image/tests/test_brand.py
odoo/addons/shopinvader_product_brand_image/views/shopinvader_backend_view.xml
odoo14_addon_shopinvader_product_brand_image-14.0.1.1.0.dist-info/METADATA
odoo14_addon_shopinvader_product_brand_image-14.0.1.1.0.dist-info/WHEEL
odoo14_addon_shopinvader_product_brand_image-14.0.1.1.0.dist-info/top_level.txt
odoo14_addon_shopinvader_product_brand_image-14.0.1.1.0.dist-info/RECORD
